perpetual_context_window/__init__.py
perpetual_context_window/perpetual_context_window.py
perpetual_context_window-4.0.5.dist-info/LICENSE.txt
perpetual_context_window-4.0.5.dist-info/METADATA
perpetual_context_window-4.0.5.dist-info/WHEEL
perpetual_context_window-4.0.5.dist-info/top_level.txt
perpetual_context_window-4.0.5.dist-info/RECORD
