Metadata-Version: 2.2
Name: perpetual_context_window
Version: 4.0.5
Home-page: https://github.com/sapiens-technology/perpetual_context_window
Author: SAPIENS TECHNOLOGY
License: Proprietary Software
License-File: LICENSE.txt
Requires-Dist: infinite-context
Requires-Dist: perpetual-context
Requires-Dist: sapiens-infinite-context-window
Requires-Dist: certifi
Dynamic: author
Dynamic: home-page
Dynamic: license
Dynamic: requires-dist
